pystepikconnect/__init__.py
pystepikconnect/client/__init__.py
pystepikconnect/client/asynchronous.py
pystepikconnect/client/synchronous.py
pystepikconnect/core/__init__.py
pystepikconnect/core/auth.py
pystepikconnect/core/courses.py
pystepikconnect/core/lessons.py
pystepikconnect/core/sections.py
pystepikconnect/core/stepics.py
pystepikconnect/core/steps.py
pystepikconnect/core/units.py
pystepikconnect/core/users.py
pystepikconnect/enums.py
pystepikconnect/exceptions.py
pystepikconnect/models.py
pystepikconnect/types/__init__.py
pystepikconnect/types/block.py
pystepikconnect/types/course.py
pystepikconnect/types/lesson.py
pystepikconnect/types/section.py
pystepikconnect/types/source.py
pystepikconnect/types/step.py
pystepikconnect/types/unit.py
pystepikconnect/types/user.py
pystepikconnect/utils.py
pystepikconnect-0.0.2.dist-info/LICENSE
pystepikconnect-0.0.2.dist-info/METADATA
pystepikconnect-0.0.2.dist-info/WHEEL
pystepikconnect-0.0.2.dist-info/RECORD
