Metadata-Version: 2.1
Name: pystepikconnect
Version: 0.0.2
Summary: (dev) python library for using Stepik REST API
Author: Ilya Kuznetsov
Author-email: ilkztsff@gmail.com
Requires-Python: >=3.11,<4.0
Classifier: Programming Language :: Python :: 3
Classifier: Programming Language :: Python :: 3.11
Classifier: Programming Language :: Python :: 3.12
Requires-Dist: aiohttp (>=3.9.5,<4.0.0)
Requires-Dist: jmespath (>=1.0.1,<2.0.0)
Requires-Dist: pydantic (>=2.8.2,<3.0.0)
Requires-Dist: requests (>=2.32.3,<3.0.0)
Requires-Dist: types-requests (>=2.32.0.20240622,<3.0.0.0)
